__init__.py
ab_ratio/__init__.py
ab_ratio/detectFacialFeatures.py
ab_ratio/predict.py
ab_ratio/utils/__init__.py
ab_ratio/utils/algorithm_utils.py
ab_ratio/utils/drawAndCalculate.py
ab_ratio/utils/preprocess.py
ab_ratio/utils/print_utils.py
ab_ratio/utils/shape_predictor_81_face_landmarks.dat
requirements/__init__.py
requirements/requirements.txt
M_Shape_AB_Ratio-0.0.1.post1.dist-info/LICENSE
M_Shape_AB_Ratio-0.0.1.post1.dist-info/METADATA
M_Shape_AB_Ratio-0.0.1.post1.dist-info/WHEEL
M_Shape_AB_Ratio-0.0.1.post1.dist-info/top_level.txt
M_Shape_AB_Ratio-0.0.1.post1.dist-info/RECORD
