Metadata-Version: 2.1
Name: M-Shape-AB-Ratio
Version: 0.0.1.post1
Summary: M Shape AB Ratio
Home-page: https://github.com/NVlabs/SPADE
Author: Ferdy
Author-email: moeharyoso89@gmail.com
License: BSD-3
Classifier: License :: OSI Approved :: MIT License
Classifier: Programming Language :: Python
Classifier: Programming Language :: Python :: 3
Classifier: Programming Language :: Python :: 3.7
Classifier: Programming Language :: Python :: 3.8
Classifier: Programming Language :: Python :: 3.9
Classifier: Programming Language :: Python :: Implementation :: CPython
Classifier: Programming Language :: Python :: Implementation :: PyPy
Requires-Python: >=3.9.0
License-File: LICENSE
Requires-Dist: dlib
Requires-Dist: imutils
Requires-Dist: opencv-contrib-python
Requires-Dist: numpy
Requires-Dist: torch
Requires-Dist: torchvision
Requires-Dist: pandas
